MANIFEST.in
flask_markdown.py
readme.md
setup.py
flask_markdown2.egg-info/PKG-INFO
flask_markdown2.egg-info/SOURCES.txt
flask_markdown2.egg-info/dependency_links.txt
flask_markdown2.egg-info/requires.txt
flask_markdown2.egg-info/top_level.txt