Metadata-Version: 1.1
Name: flask-markdown2
Version: 0.0.2
Summary: A flask extension that adds a {% markdown %} tag to templates.
Home-page: UNKNOWN
Author: Daniel Chatfield
Author-email: chatfielddaniel@gmail.com
License: UNKNOWN
Platform: UNKNOWN
Classifier: License :: OSI Approved :: MIT License
Classifier: Programming Language :: Python
Classifier: Programming Language :: Python :: 2
Classifier: Programming Language :: Python :: 3
